contentful_orm/__init__.py
contentful_orm/errors.py
contentful_orm/locales.py
contentful_orm/models.py
contentful_orm/operators.py
contentful_orm/orm_content_type_entries_proxy.py
contentful_orm/orm_environment.py
contentful_orm/serializers.py
contentful_orm/utils.py
contentful_orm/fields/__init__.py
contentful_orm/fields/fields.py
contentful_orm/fields/validations.py
contentful_orm-0.1.0.dist-info/METADATA
contentful_orm-0.1.0.dist-info/WHEEL
contentful_orm-0.1.0.dist-info/top_level.txt
contentful_orm-0.1.0.dist-info/RECORD
