Metadata-Version: 2.1
Name: contentful-orm
Version: 0.1.0
Summary: A Python toolkit for Contentful to let you create/maintain your Content Type and queries in ORM style.
Home-page: https://github.com/Phoenix-Chen/ContentfulORM
Author: Phoenix Chen
Author-email: phoenix0722chen@gmail.com
License: UNKNOWN
Platform: UNKNOWN
Classifier: Intended Audience :: Developers
Classifier: Operating System :: OS Independent
Classifier: Programming Language :: Python :: 3
Requires-Dist: contentful-management
Requires-Dist: python-baseconv
